LICENSE.txt
MANIFEST.in
README.md
setup.py
Topsis_Khushi_102017112/__init__.py
Topsis_Khushi_102017112/topsis.py
Topsis_Khushi_102017112.egg-info/PKG-INFO
Topsis_Khushi_102017112.egg-info/SOURCES.txt
Topsis_Khushi_102017112.egg-info/dependency_links.txt
Topsis_Khushi_102017112.egg-info/requires.txt
Topsis_Khushi_102017112.egg-info/top_level.txt